jai/__init__.py
jai/augments.py
jai/dataset.py
jai/improc.py
jai/logger.py
jai/trainer.py
jai/arch/__init__.py
jai/arch/resnet.py
jai/kaggler/__init__.py
jai/kaggler/from_kagglers.py
jai/kaggler/kaggle_data.py
jai/kaggler/submitter.py
jai/sota/__init__.py
jai/sota/activation.py
jai/sota/optimizer.py
jai/sota/scheduler.py
jai-0.0.9.81.dist-info/LICENSE
jai-0.0.9.81.dist-info/METADATA
jai-0.0.9.81.dist-info/WHEEL
jai-0.0.9.81.dist-info/top_level.txt
jai-0.0.9.81.dist-info/RECORD
